{
  "files": [
    {
      "file": "AlgebraicJacobian/Picard/TensorObjInverse.lean",
      "count": 2,
      "lines": [
        244,
        521
      ],
      "occurrences": [
        {
          "line": 244,
          "column": 3
        },
        {
          "line": 521,
          "column": 9
        }
      ]
    },
    {
      "file": "AlgebraicJacobian/Picard/TensorObjSubstrate.lean",
      "count": 1,
      "lines": [
        4379
      ],
      "occurrences": [
        {
          "line": 4379,
          "column": 3
        }
      ]
    }
  ],
  "total": 3,
  "partial": false,
  "warnings": []
}
