{
  "nodes": [
    {
      "id": "def:smooth-projective-curve",
      "type": "definition",
      "title": "SmoothProjectiveCurve",
      "chapter": "Overview",
      "statement": "\\textit{Source: Maulik--Shen, arXiv:2209.02568, §0.1.}\n  A \\emph{smooth projective curve} is a smooth, projective, connected algebraic curve $C$\n  over $\\mathbb{C}$ of genus $g$, where $g \\geq 2$.  This is the standing assumption\n  throughout the paper.",
      "uses": [],
      "lean_name": "MR4792069ThePwConjectureForGln.SmoothProjectiveCurve",
      "proved": false,
      "mathlib_ok": false,
      "proof_tex": "",
      "lean_source": "",
      "proof_size_lean": null,
      "has_sorry": false,
      "tex_file": "chapters/Overview.tex",
      "lean_file": "",
      "dep_count": 0,
      "rdep_count": 3,
      "descendant_count": 9,
      "proof_size_tex": null,
      "effort_local": 253,
      "proof_size_tex_total": null,
      "proof_size_lean_total": null,
      "effort_total": 253
    },
    {
      "id": "def:character-variety",
      "type": "definition",
      "title": "CharacterVariety",
      "chapter": "Overview",
      "statement": "\\textit{Source: Maulik--Shen, arXiv:2209.02568, §0.1.}\n  Let $C$ be a smooth projective curve of genus $g \\geq 2$ (\\cref{def:smooth-projective-curve}).\n  For coprime integers $n \\geq 1$ and $d \\in \\mathbb{Z}$, the\n  \\emph{$\\mathrm{GL}_n$-character variety} $M_B = M_B(C, \\mathrm{GL}_n)$ is the affine\n  complex algebraic variety\n  \\[\n    M_B \\;:=\\;\n    \\Bigl\\{(a_k, b_k)_{k=1}^g \\in \\mathrm{GL}_n(\\mathbb{C})^{2g} :\n      \\prod_{j=1}^g [a_j, b_j] = e^{2\\pi i d/n} \\mathrm{Id}_n\n    \\Bigr\\} \\git \\mathrm{GL}_n(\\mathbb{C}),\n  \\]\n  where $\\mathrm{GL}_n(\\mathbb{C})$ acts by simultaneous conjugation.  The cohomology\n  $H^*(M_B, \\mathbb{Q})$ carries a mixed Hodge structure with weight filtration\n  \\[\n    W_0 H^*(M_B, \\mathbb{Q}) \\subset W_1 H^*(M_B, \\mathbb{Q})\n    \\subset \\cdots \\subset H^*(M_B, \\mathbb{Q}).\n  \\]",
      "uses": [
        "def:smooth-projective-curve"
      ],
      "lean_name": "MR4792069ThePwConjectureForGln.CharacterVariety",
      "proved": false,
      "mathlib_ok": false,
      "proof_tex": "",
      "lean_source": "",
      "proof_size_lean": null,
      "has_sorry": false,
      "tex_file": "chapters/Overview.tex",
      "lean_file": "",
      "dep_count": 1,
      "rdep_count": 4,
      "descendant_count": 8,
      "proof_size_tex": null,
      "effort_local": 813,
      "proof_size_tex_total": null,
      "proof_size_lean_total": null,
      "effort_total": 1066
    },
    {
      "id": "def:dolbeault-moduli",
      "type": "definition",
      "title": "DolbeaultModuli",
      "chapter": "Overview",
      "statement": "\\textit{Source: Maulik--Shen, arXiv:2209.02568, §0.1.}\n  Let $C$ be a smooth projective curve of genus $g \\geq 2$ (\\cref{def:smooth-projective-curve}).\n  For coprime integers $n \\geq 1$ and $d \\in \\mathbb{Z}$, the \\emph{Dolbeault moduli space}\n  $M_{\\mathrm{Dol}} = M_{\\mathrm{Dol}}(C, \\mathrm{GL}_n)$ is the moduli space of stable Higgs\n  bundles $(\\mathcal{E}, \\theta)$ on $C$, where $\\mathcal{E}$ is a rank-$n$ vector bundle of\n  degree $d$ and $\\theta \\colon \\mathcal{E} \\to \\mathcal{E} \\otimes \\Omega^1_C$ is a Higgs\n  field; stability is with respect to the slope $\\mu = \\deg(\\mathcal{E})/\\mathrm{rk}(\\mathcal{E})$.\n  The non-abelian Hodge correspondence of Simpson gives a diffeomorphism (of smooth manifolds)\n  $M_{\\mathrm{Dol}} \\cong M_B$, canonically identifying their cohomology:\n  \\(H^*(M_{\\mathrm{Dol}}, \\mathbb{Q}) = H^*(M_B, \\mathbb{Q})\\).",
      "uses": [
        "def:smooth-projective-curve",
        "def:character-variety"
      ],
      "lean_name": "MR4792069ThePwConjectureForGln.DolbeaultModuli",
      "proved": false,
      "mathlib_ok": false,
      "proof_tex": "",
      "lean_source": "",
      "proof_size_lean": null,
      "has_sorry": false,
      "tex_file": "chapters/Overview.tex",
      "lean_file": "",
      "dep_count": 2,
      "rdep_count": 1,
      "descendant_count": 6,
      "proof_size_tex": null,
      "effort_local": 854,
      "proof_size_tex_total": null,
      "proof_size_lean_total": null,
      "effort_total": 1920
    },
    {
      "id": "def:hitchin-fibration",
      "type": "definition",
      "title": "HitchinFibration",
      "chapter": "Overview",
      "statement": "\\textit{Source: Maulik--Shen, arXiv:2209.02568, §0.1.}\n  The \\emph{Hitchin fibration} is the proper surjective morphism\n  \\[\n    h \\colon M_{\\mathrm{Dol}} \\;\\longrightarrow\\;\n    A \\;:=\\; \\bigoplus_{i=1}^n H^0\\!\\bigl(C, (\\Omega^1_C)^{\\otimes i}\\bigr),\n    \\quad (\\mathcal{E}, \\theta) \\mapsto \\mathrm{char.\\,pol.}(\\theta),\n  \\]\n  where $A$ is the \\emph{Hitchin base}.  The map $h$ records the coefficients of the\n  characteristic polynomial of the Higgs field; it is a Lagrangian fibration with respect to\n  the holomorphic symplectic form on $M_{\\mathrm{Dol}}$.  Via the non-abelian Hodge\n  diffeomorphism (\\cref{def:dolbeault-moduli}), $h$ induces a topological map\n  $h_B \\colon M_B \\to A$, the Hitchin map on the Betti side.",
      "uses": [
        "def:dolbeault-moduli"
      ],
      "lean_name": "MR4792069ThePwConjectureForGln.HitchinFibration",
      "proved": false,
      "mathlib_ok": false,
      "proof_tex": "",
      "lean_source": "",
      "proof_size_lean": null,
      "has_sorry": false,
      "tex_file": "chapters/Overview.tex",
      "lean_file": "",
      "dep_count": 1,
      "rdep_count": 1,
      "descendant_count": 5,
      "proof_size_tex": null,
      "effort_local": 727,
      "proof_size_tex_total": null,
      "proof_size_lean_total": null,
      "effort_total": 2647
    },
    {
      "id": "def:perverse-filtration",
      "type": "definition",
      "title": "PerverseFiltration",
      "chapter": "Overview",
      "statement": "\\textit{Source: Maulik--Shen, arXiv:2209.02568, §1.1.}\n  Given the Hitchin map $h_B \\colon M_B \\to A$ (\\cref{def:hitchin-fibration}), the\n  \\emph{perverse filtration} on $H^m(M_B, \\mathbb{Q})$ is the increasing filtration\n  \\[\n    P_0 H^m(M_B, \\mathbb{Q}) \\subset P_1 H^m(M_B, \\mathbb{Q})\n    \\subset \\cdots \\subset H^m(M_B, \\mathbb{Q})\n  \\]\n  defined, for $\\dim M_B = a$ and $\\dim A = b$, by\n  \\[\n    P_i H^m(M_B, \\mathbb{Q}) \\;:=\\;\n    \\mathrm{Im}\\!\\Bigl(\n      H^{m-a+r}\\!\\bigl(A,\\; {{}^{\\mathbf{p}}\\tau_{\\leq i}}\n      (R h_{B*}\\, \\mathbb{Q}_{M_B}[a-r])\\bigr)\n      \\to H^m(M_B, \\mathbb{Q})\n    \\Bigr),\n  \\]\n  where $r = \\dim M_B \\times_A M_B - \\dim M_B$ is the defect of semismallness of $h_B$, and\n  ${}^{\\mathbf{p}}\\tau_{\\leq i}$ denotes the perverse truncation in the perverse $t$-structure\n  on the derived category of constructible sheaves on $A$ (BBD).  This definition requires\n  the formalism of perverse sheaves and the decomposition theorem, which are not yet in\n  Mathlib.",
      "uses": [
        "def:hitchin-fibration",
        "def:character-variety"
      ],
      "lean_name": "MR4792069ThePwConjectureForGln.PerverseFiltration",
      "proved": false,
      "mathlib_ok": false,
      "proof_tex": "",
      "lean_source": "",
      "proof_size_lean": null,
      "has_sorry": false,
      "tex_file": "chapters/Overview.tex",
      "lean_file": "",
      "dep_count": 2,
      "rdep_count": 2,
      "descendant_count": 4,
      "proof_size_tex": null,
      "effort_local": 988,
      "proof_size_tex_total": null,
      "proof_size_lean_total": null,
      "effort_total": 3635
    },
    {
      "id": "def:weight-filtration",
      "type": "definition",
      "title": "WeightFiltration",
      "chapter": "Overview",
      "statement": "\\textit{Source: Maulik--Shen, arXiv:2209.02568, §0.1.}\n  Since $M_B$ (\\cref{def:character-variety}) is a smooth affine complex algebraic variety,\n  its cohomology $H^*(M_B, \\mathbb{Q})$ carries a mixed Hodge structure (Deligne).  The\n  \\emph{weight filtration} is the increasing filtration\n  \\[\n    W_0 H^*(M_B, \\mathbb{Q}) \\subset W_1 H^*(M_B, \\mathbb{Q})\n    \\subset \\cdots \\subset H^*(M_B, \\mathbb{Q}),\n  \\]\n  satisfying $W_{-1} H^* = 0$ and $W_{2m} H^m = H^m(M_B, \\mathbb{Q})$.  This definition\n  requires mixed Hodge theory (Deligne), which is not yet in Mathlib.",
      "uses": [
        "def:character-variety"
      ],
      "lean_name": "MR4792069ThePwConjectureForGln.WeightFiltration",
      "proved": false,
      "mathlib_ok": false,
      "proof_tex": "",
      "lean_source": "",
      "proof_size_lean": null,
      "has_sorry": false,
      "tex_file": "chapters/Overview.tex",
      "lean_file": "",
      "dep_count": 1,
      "rdep_count": 1,
      "descendant_count": 2,
      "proof_size_tex": null,
      "effort_local": 568,
      "proof_size_tex_total": null,
      "proof_size_lean_total": null,
      "effort_total": 1634
    },
    {
      "id": "thm:pw-main",
      "type": "theorem",
      "title": "$P=W$ for $\\mathrm{GL}_n$",
      "chapter": "Overview",
      "statement": "\\textit{Source: Maulik--Shen, arXiv:2209.02568, Theorem~0.2.}\n  Let $C$ be a smooth projective curve of genus $g \\geq 2$ over $\\mathbb{C}$\n  (\\cref{def:smooth-projective-curve}), and let $n \\geq 1$ be a positive integer with\n  $\\gcd(n, d) = 1$.  Then for all $k, m \\geq 0$,\n  \\[\n    P_k H^m(M_B(C, \\mathrm{GL}_n), \\mathbb{Q})\n    \\;=\\; W_{2k} H^m(M_B(C, \\mathrm{GL}_n), \\mathbb{Q})\n    \\;=\\; W_{2k+1} H^m(M_B(C, \\mathrm{GL}_n), \\mathbb{Q}),\n  \\]\n  where $P_\\bullet$ is the perverse filtration (\\cref{def:perverse-filtration}) and\n  $W_\\bullet$ is the weight filtration (\\cref{def:weight-filtration}).",
      "uses": [
        "def:character-variety",
        "def:perverse-filtration",
        "def:weight-filtration"
      ],
      "lean_name": "MR4792069ThePwConjectureForGln.PEqualsW",
      "proved": false,
      "mathlib_ok": false,
      "proof_tex": "\n  \\uses{def:strong-perversity, def:hitchin-fibration, def:dolbeault-moduli}\n  The proof has two main steps.\n\n  \\textit{Step~(a): \\(W_{2k} \\subseteq P_k\\).}  By the theorem of Markman and Shende, the\n  tautological classes $\\mathrm{ch}_k(\\mathcal{U})$ of the universal family generate\n  $H^*(M_{\\mathrm{Dol}}, \\mathbb{Q})$ and each $\\mathrm{ch}_k(\\mathcal{U})$ lies in the\n  Hodge piece ${}^k\\mathrm{Hdg}^*(M_B)$.  If each $\\mathrm{ch}_k(\\mathcal{U})$ has strong\n  perversity $k$ (\\cref{def:strong-perversity}) with respect to the Hitchin map, then every\n  product of tautological classes $\\prod_i \\mathrm{ch}_{k_i}(\\mathcal{U})$ lies in\n  $P_{\\sum k_i} H^*(M_{\\mathrm{Dol}}, \\mathbb{Q})$.  This yields\n  $W_{2k} H^* \\subseteq P_k H^*$.\n\n  \\textit{Step~(b): Equality via curious Hard Lefschetz.}  Since $W_{2k} = W_{2k+1}$ (by\n  Markman--Shende), the inclusion $W_{2k} \\subseteq P_k$ and Mellit's curious Hard Lefschetz\n  theorem together force $W_{2k} = P_k$ (using that both filtrations terminate at the same\n  degree and the Hard Lefschetz symmetry makes the inclusion an equality).\n\n  \\textit{Step~(c): Strong perversity (Theorem~2.7).}  The strong perversity of\n  $\\mathrm{ch}_k$ with respect to the Hitchin map is Theorem~2.7 of the paper\n  (\\cref{thm:strong-perversity-chern}).  Its proof uses:\n  \\begin{enumerate}\n    \\item[(i)] Vanishing cycle techniques (§2) reduce to $\\mathcal{L}$-twisted Hitchin systems\n      for an effective line bundle $\\mathcal{L}$ of sufficiently large degree.\n    \\item[(ii)] Global Springer theory (§3, Yun) provides the symmetry over the elliptic locus\n      of the Hitchin base.\n    \\item[(iii)] The parabolic support theorem (§4, Theorem~3.2) extends this symmetry to the\n      full Hitchin base.\n  \\end{enumerate}\n",
      "lean_source": "",
      "proof_size_lean": null,
      "has_sorry": false,
      "tex_file": "chapters/Overview.tex",
      "lean_file": "",
      "dep_count": 3,
      "rdep_count": 1,
      "descendant_count": 1,
      "proof_size_tex": 1751,
      "effort_local": 1751,
      "proof_size_tex_total": null,
      "proof_size_lean_total": null,
      "effort_total": 5954
    },
    {
      "id": "cor:pw-slp",
      "type": "corollary",
      "title": "$P=W$ for $\\mathrm{SL}_p$, $p$ prime",
      "chapter": "Overview",
      "statement": "\\textit{Source: Maulik--Shen, arXiv:2209.02568, §0.1.}\n  Let $C$ be a smooth projective curve of any genus $g \\geq 2$\n  (\\cref{def:smooth-projective-curve}), and let $p$ be a prime number.  Then the $P=W$\n  conjecture holds for $\\mathrm{SL}_p$.  This is an immediate consequence of the main theorem\n  (\\cref{thm:pw-main}): when $n = p$ is prime, the $P=W$ conjectures for $\\mathrm{GL}_p$,\n  $\\mathrm{SL}_p$, and $\\mathrm{PGL}_p$ are all equivalent (by Theorem~0.2 of de Cataldo--Maulik--Shen--Zhang\n  on the $\\mathrm{SL}_n$ case), so $P=W$ for $\\mathrm{GL}_p$ implies $P=W$ for $\\mathrm{SL}_p$.\n  This generalizes the $\\mathrm{SL}_2$ result of de Cataldo--Hausel--Migliorini.",
      "uses": [
        "thm:pw-main",
        "def:smooth-projective-curve"
      ],
      "lean_name": "MR4792069ThePwConjectureForGln.PEqualsWSLp",
      "proved": false,
      "mathlib_ok": false,
      "proof_tex": "",
      "lean_source": "",
      "proof_size_lean": null,
      "has_sorry": false,
      "tex_file": "chapters/Overview.tex",
      "lean_file": "",
      "dep_count": 2,
      "rdep_count": 0,
      "descendant_count": 0,
      "proof_size_tex": null,
      "effort_local": null,
      "proof_size_tex_total": null,
      "proof_size_lean_total": null,
      "effort_total": null
    },
    {
      "id": "def:strong-perversity",
      "type": "definition",
      "title": "StrongPerversity",
      "chapter": "Overview",
      "statement": "\\textit{Source: Maulik--Shen, arXiv:2209.02568, §1.1.}\n  Let $f \\colon X \\to Y$ be a proper morphism between irreducible nonsingular quasi-projective\n  varieties, with $\\dim X = a$ and defect of semismallness $r$.  For an integer $c \\geq 0$,\n  a cohomology class $\\gamma \\in H^l(X, \\mathbb{Q})$ has \\emph{strong perversity} $c$ with\n  respect to $f$ if the induced morphism $\\gamma \\colon Rf_* \\mathbb{Q}_X \\to Rf_* \\mathbb{Q}_X[l]$\n  satisfies\n  \\[\n    \\gamma\\bigl({{}^{\\mathbf{p}}\\tau_{\\leq i}}\\, Rf_*\\, \\mathbb{Q}_X\\bigr)\n    \\;\\subset\\;\n    {{}^{\\mathbf{p}}\\tau_{\\leq i+(c-l)}}\\bigl(Rf_*\\, \\mathbb{Q}_X[l]\\bigr)\n    \\quad \\forall\\, i,\n  \\]\n  where ${}^{\\mathbf{p}}\\tau_{\\leq i}$ is the perverse truncation functor (\\cref{def:perverse-filtration}).\n  Equivalently, cup product with $\\gamma$ sends $P_i H^m(X, \\mathbb{Q})$ to\n  $P_{i+c} H^{m+l}(X, \\mathbb{Q})$.  Since every class automatically has strong perversity\n  $l$, this notion is interesting only for $c < l$.",
      "uses": [
        "def:perverse-filtration"
      ],
      "lean_name": "MR4792069ThePwConjectureForGln.StrongPerversity",
      "proved": false,
      "mathlib_ok": false,
      "proof_tex": "",
      "lean_source": "",
      "proof_size_lean": null,
      "has_sorry": false,
      "tex_file": "chapters/Overview.tex",
      "lean_file": "",
      "dep_count": 1,
      "rdep_count": 1,
      "descendant_count": 1,
      "proof_size_tex": null,
      "effort_local": 970,
      "proof_size_tex_total": null,
      "proof_size_lean_total": null,
      "effort_total": 4605
    },
    {
      "id": "thm:strong-perversity-chern",
      "type": "theorem",
      "title": "Strong perversity of tautological Chern classes",
      "chapter": "Overview",
      "statement": "\\textit{Source: Maulik--Shen, arXiv:2209.02568, Theorem~2.7.}\n  This is the sheaf-theoretic enhancement of $P=W$ that is the technical heart of the proof.\n  There exists an effective line bundle $\\mathcal{L}$ on $C$ such that the Chern character\n  class\n  \\[\n    \\mathrm{ch}_k(\\mathcal{U}^{\\mathcal{L}})\n    \\in H^{2k}\\bigl(C \\times \\widehat{M}^{\\mathcal{L}}_{\\mathrm{Dol}}, \\mathbb{Q}\\bigr)\n  \\]\n  of the universal $\\mathrm{PGL}_n$-bundle $\\mathcal{U}^{\\mathcal{L}}$ over\n  $C \\times \\widehat{M}^{\\mathcal{L}}_{\\mathrm{Dol}}$ (the $\\mathcal{L}$-twisted $\\mathrm{PGL}_n$\n  Dolbeault moduli space) has \\emph{strong perversity} $k$ (\\cref{def:strong-perversity}) with\n  respect to the map\n  \\[\n    \\mathbf{h}^{\\mathcal{L}} \\;:=\\; \\mathrm{id} \\times \\widehat{h}^{\\mathcal{L}}\n    \\colon C \\times \\widehat{M}^{\\mathcal{L}}_{\\mathrm{Dol}}\n    \\to C \\times \\widehat{A}^{\\mathcal{L}},\n  \\]\n  where $\\widehat{h}^{\\mathcal{L}}$ is the $\\mathcal{L}$-twisted $\\mathrm{PGL}_n$ Hitchin map.\n  The perversity bound $k$ here is strictly stronger than the trivial bound $2k$; this\n  statement implies the $P=W$ conjecture (\\cref{thm:pw-main}) and is proved in Sections~3--4 of\n  the paper via global Springer theory and the parabolic support theorem.",
      "uses": [
        "def:strong-perversity"
      ],
      "lean_name": "MR4792069ThePwConjectureForGln.StrongPerversityChern",
      "proved": false,
      "mathlib_ok": false,
      "proof_tex": "",
      "lean_source": "",
      "proof_size_lean": null,
      "has_sorry": false,
      "tex_file": "chapters/Overview.tex",
      "lean_file": "",
      "dep_count": 1,
      "rdep_count": 0,
      "descendant_count": 0,
      "proof_size_tex": null,
      "effort_local": null,
      "proof_size_tex_total": null,
      "proof_size_lean_total": null,
      "effort_total": null
    }
  ],
  "edges": [
    {
      "from": "def:smooth-projective-curve",
      "to": "def:character-variety"
    },
    {
      "from": "def:smooth-projective-curve",
      "to": "def:dolbeault-moduli"
    },
    {
      "from": "def:character-variety",
      "to": "def:dolbeault-moduli"
    },
    {
      "from": "def:dolbeault-moduli",
      "to": "def:hitchin-fibration"
    },
    {
      "from": "def:hitchin-fibration",
      "to": "def:perverse-filtration"
    },
    {
      "from": "def:character-variety",
      "to": "def:perverse-filtration"
    },
    {
      "from": "def:character-variety",
      "to": "def:weight-filtration"
    },
    {
      "from": "def:character-variety",
      "to": "thm:pw-main"
    },
    {
      "from": "def:perverse-filtration",
      "to": "thm:pw-main"
    },
    {
      "from": "def:weight-filtration",
      "to": "thm:pw-main"
    },
    {
      "from": "thm:pw-main",
      "to": "cor:pw-slp"
    },
    {
      "from": "def:smooth-projective-curve",
      "to": "cor:pw-slp"
    },
    {
      "from": "def:perverse-filtration",
      "to": "def:strong-perversity"
    },
    {
      "from": "def:strong-perversity",
      "to": "thm:strong-perversity-chern"
    }
  ],
  "meta": {
    "num_nodes": 10,
    "num_edges": 14,
    "axioms": [
      "def:smooth-projective-curve"
    ],
    "leaves": [
      "cor:pw-slp",
      "thm:strong-perversity-chern"
    ],
    "entry": "blueprint/src/web.tex",
    "has_blueprint": true,
    "total_lean_decls": 0,
    "total_blueprint_decls": 11,
    "duplicate_ids": [],
    "macros": {
      "\\C": "\\mathbb{C}",
      "\\PP": "\\mathbb{P}",
      "\\K": "\\mathrm{K}",
      "\\Sym": "\\mathrm{Sym}",
      "\\Pic": "\\mathrm{Pic}",
      "\\Gr": "\\mathrm{Gr}",
      "\\cO": "\\mathcal{O}",
      "\\cM": "\\mathcal{M}",
      "\\cS": "\\mathcal{S}",
      "\\cG": "\\mathcal{G}",
      "\\cZ": "\\mathcal{Z}",
      "\\git": "\\mathbin{/\\mkern-6mu/}"
    }
  },
  "error": null
}